encdec_sfmh/__init__.py
encdec_sfmh/encdec.py
encdec_sfmh-0.0.4.dist-info/License.txt
encdec_sfmh-0.0.4.dist-info/METADATA
encdec_sfmh-0.0.4.dist-info/WHEEL
encdec_sfmh-0.0.4.dist-info/top_level.txt
encdec_sfmh-0.0.4.dist-info/RECORD
