Metadata-Version: 2.1
Name: encdec_sfmh
Version: 0.0.4
Summary: A simple encryption tool
Author: Thato Matona
Project-URL: Github, https://github.com/ScifiMegaHype/EncDec
Classifier: Development Status :: 4 - Beta
Classifier: Intended Audience :: Developers
Classifier: Programming Language :: Python :: 3
Classifier: Operating System :: Unix
Classifier: Operating System :: MacOS :: MacOS X
Classifier: Operating System :: Microsoft :: Windows
Requires-Python: >=3.8
License-File: License.txt
